stschema/__init__.py
stschema/schema_connector.py
stschema/schema_callbacks/__init__.py
stschema/schema_callbacks/schema_callback.py
stschema/schema_callbacks/callbacks/__init__.py
stschema/schema_callbacks/callbacks/access_token_request.py
stschema/schema_callbacks/callbacks/discovery_callback.py
stschema/schema_callbacks/callbacks/state_callback.py
stschema/schema_device/__init__.py
stschema/schema_device/schema_device.py
stschema/schema_device/schemas/__init__.py
stschema/schema_device/schemas/device_discovery_schema.py
stschema/schema_device/schemas/device_error_schema.py
stschema/schema_device/schemas/device_state_schema.py
stschema/schema_response/__init__.py
stschema/schema_response/schema_response.py
stschema/schema_response/responses/__init__.py
stschema/schema_response/responses/discovery_response.py
stschema/schema_response/responses/global_error_response.py
stschema/schema_response/responses/state_refresh_response.py
stschema/util/__init__.py
stschema/util/base_modules/__init__.py
stschema/util/base_modules/base_authentication.py
stschema/util/base_modules/base_device.py
stschema/util/base_modules/base_error.py
stschema/util/base_modules/base_headers.py
stschema/util/base_modules/base_response.py
stschema/util/base_modules/base_state.py
stschema/util/base_modules/callback_authentication.py
stschema/util/base_modules/device_context.py
stschema/util/base_modules/device_cookie.py
stschema/util/base_modules/error_enum.py
stschema/util/base_modules/manufacturer_info.py
stschema/util/error_handler/__init__.py
stschema/util/error_handler/error_handler.py
stschema/util/event_logger/__init__.py
stschema/util/event_logger/event_logger.py
st_schema_python-1.2.2.dist-info/LICENSE
st_schema_python-1.2.2.dist-info/METADATA
st_schema_python-1.2.2.dist-info/WHEEL
st_schema_python-1.2.2.dist-info/top_level.txt
st_schema_python-1.2.2.dist-info/RECORD
