Metadata-Version: 2.1
Name: st-schema-python
Version: 1.2.2
Summary: SmartThings Schema Connector Python SDK
Home-page: https://github.com/erickvneri/st-schema-python/
Author: erickvneri
Author-email: erickv@bluetrailsoft.com
License: UNKNOWN
Platform: UNKNOWN
Classifier: Development Status :: 4 - Beta
Classifier: License :: OSI Approved :: Apache Software License
Classifier: Operating System :: OS Independent
Classifier: Topic :: Home Automation
Classifier: Programming Language :: Python :: 3.6
Classifier: Programming Language :: Python :: 3.7
Classifier: Programming Language :: Python :: 3.8
Classifier: Programming Language :: Python :: 3.9
Requires-Python: >=3.6
Requires-Dist: marshmallow
